Metadata-Version: 2.4
Name: mseep-mcp-server-akshare
Version: 0.1.3
Summary: MCP server for AKShare financial data
Author-email: mseep <support@skydeck.ai>
License: MIT
Requires-Python: >=3.10
Requires-Dist: akshare>=1.11.0
Requires-Dist: mcp>=0.1.0
Requires-Dist: httpx>=0.24.0
Requires-Dist: python-dotenv>=1.0.0
Requires-Dist: pandas>=2.0.0
Requires-Dist: numpy>=1.24.0
Provides-Extra: dev
Requires-Dist: black>=23.3.0; extra == "dev"
Requires-Dist: isort>=5.12.0; extra == "dev"
Requires-Dist: mypy>=1.3.0; extra == "dev"
Requires-Dist: pytest>=7.3.1; extra == "dev"
Requires-Dist: pytest-asyncio>=0.21.0; extra == "dev"
